persist/__init__.py
persist/archive.py
persist/interfaces.py
persist/objects.py
persist/_contrib/README
persist/_contrib/__init__.py
persist/_contrib/RADLogic/__init__.py
persist/_contrib/RADLogic/topsort.py
persist-3.2.1.dist-info/WHEEL
persist-3.2.1.dist-info/METADATA
persist-3.2.1.dist-info/RECORD
